takeout_prepper/__init__.py
takeout_prepper/calendar.py
takeout_prepper/parsing.py
takeout_prepper/photos.py
takeout_prepper/tasks.py
takeout_prepper-0.0.3.dist-info/METADATA
takeout_prepper-0.0.3.dist-info/WHEEL
takeout_prepper-0.0.3.dist-info/entry_points.txt
takeout_prepper-0.0.3.dist-info/RECORD
