Metadata-Version: 2.3
Name: takeout_prepper
Version: 0.0.3
Summary: Prepares Google Takeout exports for ingestion into other tools and fixes small issues
License: MIT
Author: majesticmagpie
Requires-Python: >=3.12
Classifier: Programming Language :: Python :: 3
Classifier: License :: OSI Approved :: MIT License
Requires-Dist: pillow (>=11.1.0,<12.0.0)
Requires-Dist: pyexiftool (>=0.5.6,<0.6.0)
Requires-Dist: python-magic (>=0.4.27,<0.5.0)
Requires-Dist: tzlocal (>=5.3,<6.0)
